<?xml version="1.0" encoding="UTF-8"?>
<plugins>
    <!--
    Each <plugin> element (required) describes one plugin in the repository.
    Attributes:
     - "id" (required) - used by JetBrains IDEs to uniquely identify
       a plugin. Must match <id> in the plugin.xml file.
     - "url" (required) - URL to download the plugin JAR/ZIP file.
       Must be HTTPS.
     - "version" (required) - version of this plugin. Must match <version>
       in the plugin.xml file.
    -->
    <plugin
            id="com.reply.cluster.sdlc.Reply_SDLC_AI"
            url="https://andreaalmenari.github.io/sdlc-plugin-releases/Cluster_Reply_SDLC_Intellij_Plugin.zip"
            version="1.0.11">
        <name>Cluster Reply SDLC IntelliJ Plugin</name>
        <description>Empower your code with AI!</description>
        <change-notes>
            <![CDATA[
            <ul>
                <li>new stacktrace analysis with instruction: type <b>/debug</b>, paste the stacktrace in the chat and go!</li>
                <li>fixes for BDD JUnit</li>
                <li>fixes SonarQube integration</li>
            </ul>
            ]]>
        </change-notes>
        <idea-version since-build="222"/>
    </plugin>
</plugins>